stups_zign-1.1.31.dist-info/DESCRIPTION.rst
stups_zign-1.1.31.dist-info/METADATA
stups_zign-1.1.31.dist-info/RECORD
stups_zign-1.1.31.dist-info/WHEEL
stups_zign-1.1.31.dist-info/entry_points.txt
stups_zign-1.1.31.dist-info/metadata.json
stups_zign-1.1.31.dist-info/top_level.txt
zign/__init__.py
zign/__main__.py
zign/api.py
zign/cli.py
zign/cli_zign.py
zign/config.py
zign/oauth2.py
